presc/__init__.py
presc/config_default.yaml
presc/configuration.py
presc/dataset.py
presc/model.py
presc/utils.py
presc/copies/__init__.py
presc/copies/copying.py
presc/copies/evaluations.py
presc/copies/examples.py
presc/copies/sampling.py
presc/deprecated/train_test_dataset.py
presc/deprecated/conditional_feature_distribution/conditional_feature_distribution.py
presc/deprecated/misclassifications/__init__.py
presc/deprecated/misclassifications/misclass_rate.py
presc/deprecated/spatial_distribution/__init__.py
presc/deprecated/spatial_distribution/_spatial_distribution.ipynb
presc/deprecated/spatial_distribution/categorical_distance.py
presc/deprecated/training_stability/__init__.py
presc/deprecated/training_stability/cross_validation.py
presc/deprecated/training_stability/train_test_split.py
presc/deprecated/training_stability/training_stability_common.py
presc/evaluations/__init__.py
presc/evaluations/_base_evaluation.py
presc/evaluations/conditional_distribution.py
presc/evaluations/conditional_metric.py
presc/evaluations/spatial_distribution.py
presc/evaluations/train_test_splits.py
presc/evaluations/utils.py
presc/report/README.md
presc/report/runner.py
presc/report/resources/_config.yml
presc/report/resources/_toc.yml
presc/report/resources/conditional_distribution.ipynb
presc/report/resources/conditional_metric.ipynb
presc/report/resources/landing.ipynb
presc/report/resources/references.bib
presc/report/resources/spatial_distribution.ipynb
presc/report/resources/train_test_splits.ipynb
presc-0.4.0.dist-info/LICENSE
presc-0.4.0.dist-info/METADATA
presc-0.4.0.dist-info/WHEEL
presc-0.4.0.dist-info/top_level.txt
presc-0.4.0.dist-info/RECORD
