Metadata-Version: 2.1
Name: presc
Version: 0.4.0
Summary: Performance Robustness Evaluation for Statistical Classifiers
Home-page: https://github.com/mozilla/PRESC
Author: Mozilla Corporation
Author-email: dzeber@mozilla.com
License: MPL 2.0
Classifier: Development Status :: 3 - Alpha
Classifier: Environment :: Web Environment :: Mozilla
Classifier: Intended Audience :: Developers
Classifier: Intended Audience :: Science/Research
Classifier: License :: OSI Approved :: Mozilla Public License 2.0 (MPL 2.0)
Classifier: Programming Language :: Python
Classifier: Programming Language :: Python :: 3
Classifier: Programming Language :: Python :: 3.7
Classifier: Programming Language :: Python :: 3.8
Classifier: Programming Language :: Python :: 3.9
Classifier: Topic :: Scientific/Engineering :: Artificial Intelligence
Classifier: Topic :: Scientific/Engineering :: Information Analysis
Requires-Python: >=3.7
License-File: LICENSE
Requires-Dist: confuse
Requires-Dist: numpy
Requires-Dist: pandas (>=1.0.0)
Requires-Dist: scikit-learn (>=0.23.1)
Requires-Dist: scipy
Requires-Dist: matplotlib
Requires-Dist: seaborn
Requires-Dist: pyyaml
Requires-Dist: jupyter-book (>=0.9.1)
